spearmint/__init__.py
spearmint/client_wrapper.py
spearmint/components.py
spearmint/core.py
spearmint/py.typed
spearmint/sweepers.py
spearmint/types.py
spearmint_framework-0.1.0.dist-info/METADATA
spearmint_framework-0.1.0.dist-info/WHEEL
spearmint_framework-0.1.0.dist-info/licenses/LICENSE
spearmint_framework-0.1.0.dist-info/RECORD
