Metadata-Version: 2.4
Name: spearmint-framework
Version: 0.1.0
Summary: A Python framework for running rapid llm-based experiments
Project-URL: Homepage, https://github.com/spearmint-framework/spearmint-framework
Project-URL: Bug Tracker, https://github.com/spearmint-framework/spearmint-framework/issues
Author-email: Bill DeRusha <444835+bderusha@users.noreply.github.com>
License: MIT License
License-File: LICENSE
Keywords: ai,experiments,framework,llm
Classifier: Development Status :: 3 - Alpha
Classifier: Intended Audience :: Developers
Classifier: License :: OSI Approved :: MIT License
Classifier: Operating System :: OS Independent
Classifier: Programming Language :: Python :: 3
Classifier: Programming Language :: Python :: 3.9
Classifier: Programming Language :: Python :: 3.10
Classifier: Programming Language :: Python :: 3.11
Classifier: Programming Language :: Python :: 3.12
Classifier: Topic :: Software Development :: Libraries :: Python Modules
Requires-Python: >=3.9
Provides-Extra: dev
Requires-Dist: pytest; extra == 'dev'
